{"frames":{"sprite1":{"frame":{"x":0,"y":0,"w":30,"h":27},"rotated":false,"trimmed":false,"spriteSourceSize":{"x":0,"y":0,"w":30,"h":27},"sourceSize":{"w":30,"h":27}},"sprite2":{"frame":{"x":37,"y":0,"w":30,"h":27},"rotated":false,"trimmed":false,"spriteSourceSize":{"x":0,"y":0,"w":30,"h":27},"sourceSize":{"w":30,"h":27}},"sprite3":{"frame":{"x":69,"y":0,"w":30,"h":27},"rotated":false,"trimmed":false,"spriteSourceSize":{"x":0,"y":0,"w":30,"h":27},"sourceSize":{"w":30,"h":27}},"sprite4":{"frame":{"x":109,"y":0,"w":30,"h":27},"rotated":false,"trimmed":false,"spriteSourceSize":{"x":0,"y":0,"w":30,"h":27},"sourceSize":{"w":30,"h":27}},"sprite5":{"frame":{"x":146,"y":0,"w":30,"h":27},"rotated":false,"trimmed":false,"spriteSourceSize":{"x":0,"y":0,"w":30,"h":27},"sourceSize":{"w":30,"h":27}},"sprite6":{"frame":{"x":183,"y":0,"w":30,"h":27},"rotated":false,"trimmed":false,"spriteSourceSize":{"x":0,"y":0,"w":30,"h":27},"sourceSize":{"w":30,"h":27}},"sprite7":{"frame":{"x":221,"y":0,"w":30,"h":27},"rotated":false,"trimmed":false,"spriteSourceSize":{"x":0,"y":0,"w":30,"h":27},"sourceSize":{"w":30,"h":27}}},"meta":{"app":"https://www.leshylabs.com/apps/sstool/","version":"Leshy SpriteSheet Tool v0.8.4","image":"spritesheet.png","size":{"w":251,"h":27},"scale":1}}